sebschmi_snakemake/__init__.py
sebschmi_snakemake/__main__.py
sebschmi_snakemake/_version.py
sebschmi_snakemake/benchmark.py
sebschmi_snakemake/checkpoints.py
sebschmi_snakemake/common.py
sebschmi_snakemake/cwl.py
sebschmi_snakemake/dag.py
sebschmi_snakemake/decorators.py
sebschmi_snakemake/exceptions.py
sebschmi_snakemake/gui.html
sebschmi_snakemake/gui.py
sebschmi_snakemake/io.py
sebschmi_snakemake/jobs.py
sebschmi_snakemake/logging.py
sebschmi_snakemake/notebook.py
sebschmi_snakemake/output_index.py
sebschmi_snakemake/parser.py
sebschmi_snakemake/persistence.py
sebschmi_snakemake/report.css
sebschmi_snakemake/resources.py
sebschmi_snakemake/rules.py
sebschmi_snakemake/scheduler.py
sebschmi_snakemake/script.py
sebschmi_snakemake/shell.py
sebschmi_snakemake/stats.py
sebschmi_snakemake/utils.py
sebschmi_snakemake/workflow.py
sebschmi_snakemake/wrapper.py
sebschmi_snakemake/caching/__init__.py
sebschmi_snakemake/caching/hash.py
sebschmi_snakemake/caching/local.py
sebschmi_snakemake/caching/remote.py
sebschmi_snakemake/deployment/__init__.py
sebschmi_snakemake/deployment/conda.py
sebschmi_snakemake/deployment/env_modules.py
sebschmi_snakemake/deployment/singularity.py
sebschmi_snakemake/executors/__init__.py
sebschmi_snakemake/executors/ga4gh_tes.py
sebschmi_snakemake/executors/google_lifesciences.py
sebschmi_snakemake/executors/google_lifesciences_helper.py
sebschmi_snakemake/executors/jobscript.sh
sebschmi_snakemake/linting/__init__.py
sebschmi_snakemake/linting/links.py
sebschmi_snakemake/linting/rules.py
sebschmi_snakemake/linting/snakefiles.py
sebschmi_snakemake/remote/AzBlob.py
sebschmi_snakemake/remote/EGA.py
sebschmi_snakemake/remote/FTP.py
sebschmi_snakemake/remote/GS.py
sebschmi_snakemake/remote/HTTP.py
sebschmi_snakemake/remote/NCBI.py
sebschmi_snakemake/remote/S3.py
sebschmi_snakemake/remote/S3Mocked.py
sebschmi_snakemake/remote/SFTP.py
sebschmi_snakemake/remote/XRootD.py
sebschmi_snakemake/remote/__init__.py
sebschmi_snakemake/remote/dropbox.py
sebschmi_snakemake-5.32.1.dist-info/AUTHORS.rst
sebschmi_snakemake-5.32.1.dist-info/LICENSE.md
sebschmi_snakemake-5.32.1.dist-info/METADATA
sebschmi_snakemake-5.32.1.dist-info/WHEEL
sebschmi_snakemake-5.32.1.dist-info/entry_points.txt
sebschmi_snakemake-5.32.1.dist-info/top_level.txt
sebschmi_snakemake-5.32.1.dist-info/RECORD
